gaveta/__init__.py
gaveta/files.py
gaveta/gen.py
gaveta/guardrails.py
gaveta/json.py
gaveta/py.typed
gaveta/seq.py
gaveta/time.py
gaveta/urls.py
gaveta/utils.py
gaveta-0.6.0.dist-info/METADATA
gaveta-0.6.0.dist-info/WHEEL
gaveta-0.6.0.dist-info/licenses/LICENSE
gaveta-0.6.0.dist-info/RECORD
