Metadata-Version: 2.3
Name: gaveta
Version: 0.6.0
Summary: Vanilla utility functions for different projects.
Project-URL: Documentation, https://gaveta.joao.tools/
Project-URL: Issues, https://gitlab.com/joaommpalmeiro/gaveta/-/issues
Project-URL: Source, https://gitlab.com/joaommpalmeiro/gaveta
Author-email: João Palmeiro <joaopalmeiro@proton.me>
License-Expression: MIT
License-File: LICENSE
Classifier: Development Status :: 4 - Beta
Classifier: Intended Audience :: Developers
Classifier: License :: OSI Approved :: MIT License
Classifier: Natural Language :: English
Classifier: Operating System :: OS Independent
Classifier: Programming Language :: Python
Classifier: Programming Language :: Python :: 3
Classifier: Programming Language :: Python :: 3 :: Only
Classifier: Programming Language :: Python :: 3.10
Classifier: Programming Language :: Python :: 3.11
Classifier: Programming Language :: Python :: 3.12
Classifier: Programming Language :: Python :: 3.13
Classifier: Programming Language :: Python :: Implementation :: CPython
Classifier: Topic :: Utilities
Classifier: Typing :: Typed
Requires-Python: >=3.10
